radio_sim/__init__.py
radio_sim/array.py
radio_sim/beams.py
radio_sim/radio_sim.py
radio_sim/sky.py
radio_sim/utils.py
radio_sim/tests/test_array.py
radio_sim/tests/test_beams.py
radio_sim/tests/test_radio_sim.py
radio_sim/tests/test_sky.py
radio_sim/tests/test_utils.py
radio_sim-0.0.2.dist-info/LICENSE
radio_sim-0.0.2.dist-info/METADATA
radio_sim-0.0.2.dist-info/WHEEL
radio_sim-0.0.2.dist-info/top_level.txt
radio_sim-0.0.2.dist-info/RECORD
