Metadata-Version: 2.1
Name: radio-sim
Version: 0.0.2
Summary: collection of calibration routines to run on the HERA instrument.
Home-page: https://github.com/tyler-a-cox/radio_sim
Author: Tyler Cox
Author-email: tyler.a.cox@berkeley.edu
License: BSD
Project-URL: Bug Tracker, https://github.com/tyler-a-cox/radio_sim/issues
Platform: UNKNOWN
Classifier: Programming Language :: Python :: 3
Classifier: License :: OSI Approved :: BSD License
Classifier: Operating System :: OS Independent
Requires-Python: >=3.6
Requires-Dist: numpy (>=1.10)
Requires-Dist: scipy
Requires-Dist: astropy
Requires-Dist: pyuvdata
Provides-Extra: all
Requires-Dist: aipy (>=3.0) ; extra == 'all'
